alchemy_sdk_py/__init__.py
alchemy_sdk_py/__version__.py
alchemy_sdk_py/alchemy.py
alchemy_sdk_py/errors.py
alchemy_sdk_py/evm_node.py
alchemy_sdk_py/networks.py
alchemy_sdk_py/utils.py
alchemy_sdk_py-0.2.0.dist-info/LICENSE
alchemy_sdk_py-0.2.0.dist-info/METADATA
alchemy_sdk_py-0.2.0.dist-info/WHEEL
alchemy_sdk_py-0.2.0.dist-info/top_level.txt
alchemy_sdk_py-0.2.0.dist-info/RECORD
